{
  "entries": [
    {
      "imageName": "S01E04_-_Rangeboy-0194.jpg",
      "timestamp": "2025-09-13T11:34:27.592Z",
      "altText": "The Adventures of Pete & Pete - Season 1, Episode 4: Rangeboy",
      "episode": "S1E4",
      "season": 1,
      "episodeNumber": 4,
      "cycleInfo": "Post 3069 - 6775 available (16.6% excluded from seasonal pool)"
    },
    {
      "imageName": "S01E02_-_Day_of_The_Dot-0084.jpg",
      "timestamp": "2025-09-13T12:08:48.091Z",
      "altText": "The Adventures of Pete & Pete - Season 1, Episode 2: Day of the Dot",
      "episode": "S1E2",
      "season": 1,
      "episodeNumber": 2,
      "cycleInfo": "Post 3070 - 6775 available (16.6% excluded from seasonal pool)"
    },
    {
      "imageName": "S03E01_-_35_Hours-0066.jpg",
      "timestamp": "2025-09-13T12:46:13.009Z",
      "altText": "The Adventures of Pete & Pete - Season 3, Episode 1: 35 Hours",
      "episode": "S3E1",
      "season": 3,
      "episodeNumber": 1,
      "cycleInfo": "Post 3071 - 6775 available (16.6% excluded from seasonal pool)"
    },
    {
      "imageName": "S03E02_-_The_Trouble_With_Teddy-0061.jpg",
      "timestamp": "2025-09-13T13:07:55.097Z",
      "altText": "The Adventures of Pete & Pete - Season 3, Episode 2: The Trouble With Teddy",
      "episode": "S3E2",
      "season": 3,
      "episodeNumber": 2,
      "cycleInfo": "Post 3072 - 6775 available (16.6% excluded from seasonal pool)"
    },
    {
      "imageName": "S01E06_-_Don't_Tread_on_Pete-0252.jpg",
      "timestamp": "2025-09-13T13:34:26.828Z",
      "altText": "The Adventures of Pete & Pete - Season 1, Episode 6: Don'T Tread on Pete",
      "episode": "S1E6",
      "season": 1,
      "episodeNumber": 6,
      "cycleInfo": "Post 3073 - 6775 available (16.6% excluded from seasonal pool)"
    },
    {
      "imageName": "S00E01_-_Valentine's_Day_Massacre-0133.jpg",
      "timestamp": "2025-09-13T14:05:10.064Z",
      "altText": "The Adventures of Pete & Pete - Valentine'S Day Massacre",
      "episode": "S0E1",
      "season": 0,
      "episodeNumber": 1,
      "cycleInfo": "Post 3074 - 6775 available (16.6% excluded from seasonal pool)"
    },
    {
      "imageName": "S00E02_-_What_We_Did_on_Our_Summer_Vacation-0161.jpg",
      "timestamp": "2025-09-13T14:33:58.511Z",
      "altText": "The Adventures of Pete & Pete - What We Did on Our Summer Vacation",
      "episode": "S0E2",
      "season": 0,
      "episodeNumber": 2,
      "cycleInfo": "Post 3075 - 6775 available (16.6% excluded from seasonal pool)"
    },
    {
      "imageName": "S02E13_-_Sick_Day-0117.jpg",
      "timestamp": "2025-09-13T15:05:18.411Z",
      "altText": "The Adventures of Pete & Pete - Season 2, Episode 13: Sick Day",
      "episode": "S2E13",
      "season": 2,
      "episodeNumber": 13,
      "cycleInfo": "Post 3076 - 6775 available (16.6% excluded from seasonal pool)"
    },
    {
      "imageName": "S01E05_-_Tool_and_Die-0067.jpg",
      "timestamp": "2025-09-13T15:34:01.741Z",
      "altText": "The Adventures of Pete & Pete - Season 1, Episode 5: Tool and Die",
      "episode": "S1E5",
      "season": 1,
      "episodeNumber": 5,
      "cycleInfo": "Post 3077 - 6775 available (16.6% excluded from seasonal pool)"
    },
    {
      "imageName": "S01E01_-_King_of_The_Road-0241.jpg",
      "timestamp": "2025-09-13T16:05:49.389Z",
      "altText": "The Adventures of Pete & Pete - Season 1, Episode 1: King of the Road",
      "episode": "S1E1",
      "season": 1,
      "episodeNumber": 1,
      "cycleInfo": "Post 3078 - 6775 available (16.6% excluded from seasonal pool)"
    },
    {
      "imageName": "S03E10_-_Pinned-0109.jpg",
      "timestamp": "2025-09-13T16:35:46.920Z",
      "altText": "The Adventures of Pete & Pete - Season 3, Episode 10: Pinned",
      "episode": "S3E10",
      "season": 3,
      "episodeNumber": 10,
      "cycleInfo": "Post 3079 - 6775 available (16.6% excluded from seasonal pool)"
    },
    {
      "imageName": "S03E13_-_Saturday-0059.jpg",
      "timestamp": "2025-09-13T17:05:06.525Z",
      "altText": "The Adventures of Pete & Pete - Season 3, Episode 13: Saturday",
      "episode": "S3E13",
      "season": 3,
      "episodeNumber": 13,
      "cycleInfo": "Post 3080 - 6775 available (16.6% excluded from seasonal pool)"
    },
    {
      "imageName": "S02E09_-_On_Golden_Pete-0268.jpg",
      "timestamp": "2025-09-13T17:34:10.869Z",
      "altText": "The Adventures of Pete & Pete - Season 2, Episode 9: On Golden Pete",
      "episode": "S2E9",
      "season": 2,
      "episodeNumber": 9,
      "cycleInfo": "Post 3081 - 6775 available (16.6% excluded from seasonal pool)"
    },
    {
      "imageName": "S02E01_-_Grounded_For_Life-0038.jpg",
      "timestamp": "2025-09-13T18:06:43.375Z",
      "altText": "The Adventures of Pete & Pete - Season 2, Episode 1: Grounded for Life",
      "episode": "S2E1",
      "season": 2,
      "episodeNumber": 1,
      "cycleInfo": "Post 3082 - 6775 available (16.6% excluded from seasonal pool)"
    },
    {
      "imageName": "The_Adventures_of_Pete_&_Pete_-_0x23_-_Artie,_The_Strongest_Man..._In_The_World!-0007.jpg",
      "timestamp": "2025-09-13T18:37:06.867Z",
      "altText": "The Adventures of Pete & Pete - Artie, the Strongest Man... in the World!",
      "episode": "S0E23",
      "season": 0,
      "episodeNumber": 23,
      "cycleInfo": "Post 3083 - 6775 available (16.6% excluded from seasonal pool)"
    },
    {
      "imageName": "S03E02_-_The_Trouble_With_Teddy-0145.jpg",
      "timestamp": "2025-09-13T19:04:52.167Z",
      "altText": "The Adventures of Pete & Pete - Season 3, Episode 2: The Trouble With Teddy",
      "episode": "S3E2",
      "season": 3,
      "episodeNumber": 2,
      "cycleInfo": "Post 3084 - 6775 available (16.6% excluded from seasonal pool)"
    },
    {
      "imageName": "S02E11_-_Farewell_My_Little_Viking_Part_2-0255.jpg",
      "timestamp": "2025-09-13T19:34:11.051Z",
      "altText": "The Adventures of Pete & Pete - Season 2, Episode 11: Farewell My Little Viking Part 2",
      "episode": "S2E11",
      "season": 2,
      "episodeNumber": 11,
      "cycleInfo": "Post 3085 - 6775 available (16.6% excluded from seasonal pool)"
    },
    {
      "imageName": "S01E02_-_Day_of_The_Dot-0143.jpg",
      "timestamp": "2025-09-13T20:05:50.204Z",
      "altText": "The Adventures of Pete & Pete - Season 1, Episode 2: Day of the Dot",
      "episode": "S1E2",
      "season": 1,
      "episodeNumber": 2,
      "cycleInfo": "Post 3086 - 6775 available (16.6% excluded from seasonal pool)"
    },
    {
      "imageName": "S03E07_-_Last_Laugh-0044.jpg",
      "timestamp": "2025-09-13T20:34:02.511Z",
      "altText": "The Adventures of Pete & Pete - Season 3, Episode 7: Last Laugh",
      "episode": "S3E7",
      "season": 3,
      "episodeNumber": 7,
      "cycleInfo": "Post 3087 - 6775 available (16.6% excluded from seasonal pool)"
    },
    {
      "imageName": "S00E01_-_Valentine's_Day_Massacre-0207.jpg",
      "timestamp": "2025-09-13T21:05:10.827Z",
      "altText": "The Adventures of Pete & Pete - Valentine'S Day Massacre",
      "episode": "S0E1",
      "season": 0,
      "episodeNumber": 1,
      "cycleInfo": "Post 3088 - 6775 available (16.6% excluded from seasonal pool)"
    },
    {
      "imageName": "S01E08_-_Hard_Day's_Pete-0124.jpg",
      "timestamp": "2025-09-13T21:34:10.709Z",
      "altText": "The Adventures of Pete & Pete - Season 1, Episode 8: Hard Day'S Pete",
      "episode": "S1E8",
      "season": 1,
      "episodeNumber": 8,
      "cycleInfo": "Post 3089 - 6775 available (16.6% excluded from seasonal pool)"
    },
    {
      "imageName": "S01E06_-_Don't_Tread_on_Pete-0174.jpg",
      "timestamp": "2025-09-13T22:05:17.841Z",
      "altText": "The Adventures of Pete & Pete - Season 1, Episode 6: Don'T Tread on Pete",
      "episode": "S1E6",
      "season": 1,
      "episodeNumber": 6,
      "cycleInfo": "Post 3090 - 6775 available (16.6% excluded from seasonal pool)"
    },
    {
      "imageName": "S02E08_-_X_equals_Why-0117.jpg",
      "timestamp": "2025-09-13T22:34:27.983Z",
      "altText": "The Adventures of Pete & Pete - Season 2, Episode 8: X Equals Why",
      "episode": "S2E8",
      "season": 2,
      "episodeNumber": 8,
      "cycleInfo": "Post 3091 - 6775 available (16.6% excluded from seasonal pool)"
    },
    {
      "imageName": "S02E05_-_Time_Tunnel-0098.jpg",
      "timestamp": "2025-09-13T23:05:26.092Z",
      "altText": "The Adventures of Pete & Pete - Season 2, Episode 5: Time Tunnel",
      "episode": "S2E5",
      "season": 2,
      "episodeNumber": 5,
      "cycleInfo": "Post 3092 - 6775 available (16.6% excluded from seasonal pool)"
    },
    {
      "imageName": "S01E07_-_When_Petes_Collide-0039.jpg",
      "timestamp": "2025-09-13T23:34:14.437Z",
      "altText": "The Adventures of Pete & Pete - Season 1, Episode 7: When Petes Collide",
      "episode": "S1E7",
      "season": 1,
      "episodeNumber": 7,
      "cycleInfo": "Post 3093 - 6775 available (16.6% excluded from seasonal pool)"
    },
    {
      "imageName": "S02E07_-_Inspector_34-0064.jpg",
      "timestamp": "2025-09-14T00:26:09.576Z",
      "altText": "The Adventures of Pete & Pete - Season 2, Episode 7: Inspector 34",
      "episode": "S2E7",
      "season": 2,
      "episodeNumber": 7,
      "cycleInfo": "Post 3094 - 6775 available (16.6% excluded from seasonal pool)"
    },
    {
      "imageName": "S02E02_-_Field_of_Pete-0087.jpg",
      "timestamp": "2025-09-14T00:50:57.505Z",
      "altText": "The Adventures of Pete & Pete - Season 2, Episode 2: Field of Pete",
      "episode": "S2E2",
      "season": 2,
      "episodeNumber": 2,
      "cycleInfo": "Post 3095 - 6775 available (16.6% excluded from seasonal pool)"
    },
    {
      "imageName": "S02E12_-_Yellow_Fever-0223.jpg",
      "timestamp": "2025-09-14T01:33:53.796Z",
      "altText": "The Adventures of Pete & Pete - Season 2, Episode 12: Yellow Fever",
      "episode": "S2E12",
      "season": 2,
      "episodeNumber": 12,
      "cycleInfo": "Post 3096 - 6775 available (16.6% excluded from seasonal pool)"
    },
    {
      "imageName": "S01E08_-_Hard_Day's_Pete-0211.jpg",
      "timestamp": "2025-09-14T02:33:36.234Z",
      "altText": "The Adventures of Pete & Pete - Season 1, Episode 8: Hard Day'S Pete",
      "episode": "S1E8",
      "season": 1,
      "episodeNumber": 8,
      "cycleInfo": "Post 3097 - 6775 available (16.6% excluded from seasonal pool)"
    },
    {
      "imageName": "S01E02_-_Day_of_The_Dot-0204.jpg",
      "timestamp": "2025-09-14T03:19:21.149Z",
      "altText": "The Adventures of Pete & Pete - Season 1, Episode 2: Day of the Dot",
      "episode": "S1E2",
      "season": 1,
      "episodeNumber": 2,
      "cycleInfo": "Post 3098 - 6775 available (16.6% excluded from seasonal pool)"
    },
    {
      "imageName": "S03E13_-_Saturday-0105.jpg",
      "timestamp": "2025-09-14T03:41:03.796Z",
      "altText": "The Adventures of Pete & Pete - Season 3, Episode 13: Saturday",
      "episode": "S3E13",
      "season": 3,
      "episodeNumber": 13,
      "cycleInfo": "Post 3099 - 6775 available (16.6% excluded from seasonal pool)"
    },
    {
      "imageName": "S02E03_-_The_Call-0087.jpg",
      "timestamp": "2025-09-14T04:06:53.720Z",
      "altText": "The Adventures of Pete & Pete - Season 2, Episode 3: The Call",
      "episode": "S2E3",
      "season": 2,
      "episodeNumber": 3,
      "cycleInfo": "Post 3100 - 6775 available (16.6% excluded from seasonal pool)"
    },
    {
      "imageName": "S02E10_-_Farewell_My_Little_Viking_Part_1-0243.jpg",
      "timestamp": "2025-09-14T04:36:19.456Z",
      "altText": "The Adventures of Pete & Pete - Season 2, Episode 10: Farewell My Little Viking Part 1",
      "episode": "S2E10",
      "season": 2,
      "episodeNumber": 10,
      "cycleInfo": "Post 3101 - 6775 available (16.6% excluded from seasonal pool)"
    },
    {
      "imageName": "S03E05_-_Dance_Fever-0001.jpg",
      "timestamp": "2025-09-14T05:06:26.428Z",
      "altText": "The Adventures of Pete & Pete - Season 3, Episode 5: Dance Fever",
      "episode": "S3E5",
      "season": 3,
      "episodeNumber": 5,
      "cycleInfo": "Post 3102 - 6775 available (16.6% excluded from seasonal pool)"
    },
    {
      "imageName": "S01E01_-_King_of_The_Road-0078.jpg",
      "timestamp": "2025-09-14T05:35:01.018Z",
      "altText": "The Adventures of Pete & Pete - Season 1, Episode 1: King of the Road",
      "episode": "S1E1",
      "season": 1,
      "episodeNumber": 1,
      "cycleInfo": "Post 3103 - 6775 available (16.6% excluded from seasonal pool)"
    },
    {
      "imageName": "S03E12_-_Das_Bus-0166.jpg",
      "timestamp": "2025-09-14T06:07:55.475Z",
      "altText": "The Adventures of Pete & Pete - Season 3, Episode 12: Das Bus",
      "episode": "S3E12",
      "season": 3,
      "episodeNumber": 12,
      "cycleInfo": "Post 3104 - 6775 available (16.6% excluded from seasonal pool)"
    },
    {
      "imageName": "S01E05_-_Tool_and_Die-0098.jpg",
      "timestamp": "2025-09-14T06:39:25.955Z",
      "altText": "The Adventures of Pete & Pete - Season 1, Episode 5: Tool and Die",
      "episode": "S1E5",
      "season": 1,
      "episodeNumber": 5,
      "cycleInfo": "Post 3105 - 6775 available (16.6% excluded from seasonal pool)"
    },
    {
      "imageName": "S03E03_-_The_Good,_the_Bad,_and_the_Lucky-0141.jpg",
      "timestamp": "2025-09-14T07:05:49.008Z",
      "altText": "The Adventures of Pete & Pete - Season 3, Episode 3: The Good, The Bad, and The Lucky",
      "episode": "S3E3",
      "season": 3,
      "episodeNumber": 3,
      "cycleInfo": "Post 3106 - 6775 available (16.6% excluded from seasonal pool)"
    },
    {
      "imageName": "S02E01_-_Grounded_For_Life-0176.jpg",
      "timestamp": "2025-09-14T07:34:18.473Z",
      "altText": "The Adventures of Pete & Pete - Season 2, Episode 1: Grounded for Life",
      "episode": "S2E1",
      "season": 2,
      "episodeNumber": 1,
      "cycleInfo": "Post 3107 - 6775 available (16.6% excluded from seasonal pool)"
    },
    {
      "imageName": "S01E01_-_King_of_The_Road-0035.jpg",
      "timestamp": "2025-09-14T08:07:00.878Z",
      "altText": "The Adventures of Pete & Pete - Season 1, Episode 1: King of the Road",
      "episode": "S1E1",
      "season": 1,
      "episodeNumber": 1,
      "cycleInfo": "Post 3108 - 6775 available (16.6% excluded from seasonal pool)"
    },
    {
      "imageName": "S01E02_-_Day_of_The_Dot-0240.jpg",
      "timestamp": "2025-09-14T08:36:32.749Z",
      "altText": "The Adventures of Pete & Pete - Season 1, Episode 2: Day of the Dot",
      "episode": "S1E2",
      "season": 1,
      "episodeNumber": 2,
      "cycleInfo": "Post 3109 - 6775 available (16.6% excluded from seasonal pool)"
    },
    {
      "imageName": "S03E03_-_The_Good,_the_Bad,_and_the_Lucky-0238.jpg",
      "timestamp": "2025-09-14T09:05:45.259Z",
      "altText": "The Adventures of Pete & Pete - Season 3, Episode 3: The Good, The Bad, and The Lucky",
      "episode": "S3E3",
      "season": 3,
      "episodeNumber": 3,
      "cycleInfo": "Post 3110 - 6775 available (16.6% excluded from seasonal pool)"
    },
    {
      "imageName": "S00E01_-_Valentine's_Day_Massacre-0074.jpg",
      "timestamp": "2025-09-14T09:34:42.250Z",
      "altText": "The Adventures of Pete & Pete - Valentine'S Day Massacre",
      "episode": "S0E1",
      "season": 0,
      "episodeNumber": 1,
      "cycleInfo": "Post 3111 - 6775 available (16.6% excluded from seasonal pool)"
    },
    {
      "imageName": "S02E12_-_Yellow_Fever-0269.jpg",
      "timestamp": "2025-09-14T10:05:25.488Z",
      "altText": "The Adventures of Pete & Pete - Season 2, Episode 12: Yellow Fever",
      "episode": "S2E12",
      "season": 2,
      "episodeNumber": 12,
      "cycleInfo": "Post 3112 - 6775 available (16.6% excluded from seasonal pool)"
    },
    {
      "imageName": "S00E03_-_Space,_Geeks,_and_Johnny_Unitas-0048.jpg",
      "timestamp": "2025-09-14T10:34:25.023Z",
      "altText": "The Adventures of Pete & Pete - Space, Geeks, and Johnny Unitas",
      "episode": "S0E3",
      "season": 0,
      "episodeNumber": 3,
      "cycleInfo": "Post 3113 - 6775 available (16.6% excluded from seasonal pool)"
    },
    {
      "imageName": "S03E09_-_Road_Warrior-0201.jpg",
      "timestamp": "2025-09-14T11:05:02.568Z",
      "altText": "The Adventures of Pete & Pete - Season 3, Episode 9: Road Warrior",
      "episode": "S3E9",
      "season": 3,
      "episodeNumber": 9,
      "cycleInfo": "Post 3114 - 6775 available (16.6% excluded from seasonal pool)"
    },
    {
      "imageName": "S03E02_-_The_Trouble_With_Teddy-0174.jpg",
      "timestamp": "2025-09-14T11:34:07.296Z",
      "altText": "The Adventures of Pete & Pete - Season 3, Episode 2: The Trouble With Teddy",
      "episode": "S3E2",
      "season": 3,
      "episodeNumber": 2,
      "cycleInfo": "Post 3115 - 6775 available (16.6% excluded from seasonal pool)"
    },
    {
      "imageName": "S02E09_-_On_Golden_Pete-0191.jpg",
      "timestamp": "2025-09-14T12:08:36.659Z",
      "altText": "The Adventures of Pete & Pete - Season 2, Episode 9: On Golden Pete",
      "episode": "S2E9",
      "season": 2,
      "episodeNumber": 9,
      "cycleInfo": "Post 3116 - 6775 available (16.6% excluded from seasonal pool)"
    },
    {
      "imageName": "S02E07_-_Inspector_34-0070.jpg",
      "timestamp": "2025-09-14T12:45:48.929Z",
      "altText": "The Adventures of Pete & Pete - Season 2, Episode 7: Inspector 34",
      "episode": "S2E7",
      "season": 2,
      "episodeNumber": 7,
      "cycleInfo": "Post 3117 - 6775 available (16.6% excluded from seasonal pool)"
    },
    {
      "imageName": "S03E01_-_35_Hours-0123.jpg",
      "timestamp": "2025-09-14T13:07:52.944Z",
      "altText": "The Adventures of Pete & Pete - Season 3, Episode 1: 35 Hours",
      "episode": "S3E1",
      "season": 3,
      "episodeNumber": 1,
      "cycleInfo": "Post 3118 - 6775 available (16.6% excluded from seasonal pool)"
    },
    {
      "imageName": "S02E01_-_Grounded_For_Life-0068.jpg",
      "timestamp": "2025-09-14T13:33:54.678Z",
      "altText": "The Adventures of Pete & Pete - Season 2, Episode 1: Grounded for Life",
      "episode": "S2E1",
      "season": 2,
      "episodeNumber": 1,
      "cycleInfo": "Post 3119 - 6775 available (16.6% excluded from seasonal pool)"
    },
    {
      "imageName": "S01E08_-_Hard_Day's_Pete-0237.jpg",
      "timestamp": "2025-09-14T14:05:17.538Z",
      "altText": "The Adventures of Pete & Pete - Season 1, Episode 8: Hard Day'S Pete",
      "episode": "S1E8",
      "season": 1,
      "episodeNumber": 8,
      "cycleInfo": "Post 3120 - 6775 available (16.6% excluded from seasonal pool)"
    },
    {
      "imageName": "S03E02_-_The_Trouble_With_Teddy-0059.jpg",
      "timestamp": "2025-09-14T14:34:22.579Z",
      "altText": "The Adventures of Pete & Pete - Season 3, Episode 2: The Trouble With Teddy",
      "episode": "S3E2",
      "season": 3,
      "episodeNumber": 2,
      "cycleInfo": "Post 3121 - 6775 available (16.6% excluded from seasonal pool)"
    },
    {
      "imageName": "S03E07_-_Last_Laugh-0143.jpg",
      "timestamp": "2025-09-14T15:05:18.475Z",
      "altText": "The Adventures of Pete & Pete - Season 3, Episode 7: Last Laugh",
      "episode": "S3E7",
      "season": 3,
      "episodeNumber": 7,
      "cycleInfo": "Post 3122 - 6775 available (16.6% excluded from seasonal pool)"
    },
    {
      "imageName": "S00E01_-_Valentine's_Day_Massacre-0090.jpg",
      "timestamp": "2025-09-14T15:34:02.901Z",
      "altText": "The Adventures of Pete & Pete - Valentine'S Day Massacre",
      "episode": "S0E1",
      "season": 0,
      "episodeNumber": 1,
      "cycleInfo": "Post 3123 - 6775 available (16.6% excluded from seasonal pool)"
    },
    {
      "imageName": "S02E01_-_Grounded_For_Life-0006.jpg",
      "timestamp": "2025-09-14T16:06:10.293Z",
      "altText": "The Adventures of Pete & Pete - Season 2, Episode 1: Grounded for Life",
      "episode": "S2E1",
      "season": 2,
      "episodeNumber": 1,
      "cycleInfo": "Post 3124 - 6775 available (16.6% excluded from seasonal pool)"
    },
    {
      "imageName": "S01E08_-_Hard_Day's_Pete-0003.jpg",
      "timestamp": "2025-09-14T16:36:29.612Z",
      "altText": "The Adventures of Pete & Pete - Season 1, Episode 8: Hard Day'S Pete",
      "episode": "S1E8",
      "season": 1,
      "episodeNumber": 8,
      "cycleInfo": "Post 3125 - 6775 available (16.6% excluded from seasonal pool)"
    },
    {
      "imageName": "S03E05_-_Dance_Fever-0074.jpg",
      "timestamp": "2025-09-14T17:05:04.825Z",
      "altText": "The Adventures of Pete & Pete - Season 3, Episode 5: Dance Fever",
      "episode": "S3E5",
      "season": 3,
      "episodeNumber": 5,
      "cycleInfo": "Post 3126 - 6775 available (16.6% excluded from seasonal pool)"
    },
    {
      "imageName": "S03E12_-_Das_Bus-0143.jpg",
      "timestamp": "2025-09-14T17:34:12.590Z",
      "altText": "The Adventures of Pete & Pete - Season 3, Episode 12: Das Bus",
      "episode": "S3E12",
      "season": 3,
      "episodeNumber": 12,
      "cycleInfo": "Post 3127 - 6775 available (16.6% excluded from seasonal pool)"
    },
    {
      "imageName": "S03E02_-_The_Trouble_With_Teddy-0082.jpg",
      "timestamp": "2025-09-14T18:06:50.944Z",
      "altText": "The Adventures of Pete & Pete - Season 3, Episode 2: The Trouble With Teddy",
      "episode": "S3E2",
      "season": 3,
      "episodeNumber": 2,
      "cycleInfo": "Post 3128 - 6775 available (16.6% excluded from seasonal pool)"
    },
    {
      "imageName": "S03E03_-_The_Good,_the_Bad,_and_the_Lucky-0121.jpg",
      "timestamp": "2025-09-14T18:37:36.312Z",
      "altText": "The Adventures of Pete & Pete - Season 3, Episode 3: The Good, The Bad, and The Lucky",
      "episode": "S3E3",
      "season": 3,
      "episodeNumber": 3,
      "cycleInfo": "Post 3129 - 6775 available (16.6% excluded from seasonal pool)"
    },
    {
      "imageName": "The_Adventures_of_Pete_&_Pete_-_0x24_-_X-Ray_Man-0001.jpg",
      "timestamp": "2025-09-14T19:05:00.552Z",
      "altText": "The Adventures of Pete & Pete - X Ray Man",
      "episode": "S0E24",
      "season": 0,
      "episodeNumber": 24,
      "cycleInfo": "Post 3130 - 6775 available (16.6% excluded from seasonal pool)"
    },
    {
      "imageName": "S01E06_-_Don't_Tread_on_Pete-0261.jpg",
      "timestamp": "2025-09-14T19:34:21.567Z",
      "altText": "The Adventures of Pete & Pete - Season 1, Episode 6: Don'T Tread on Pete",
      "episode": "S1E6",
      "season": 1,
      "episodeNumber": 6,
      "cycleInfo": "Post 3131 - 6775 available (16.6% excluded from seasonal pool)"
    },
    {
      "imageName": "S03E13_-_Saturday-0163.jpg",
      "timestamp": "2025-09-14T20:06:29.160Z",
      "altText": "The Adventures of Pete & Pete - Season 3, Episode 13: Saturday",
      "episode": "S3E13",
      "season": 3,
      "episodeNumber": 13,
      "cycleInfo": "Post 3132 - 6775 available (16.6% excluded from seasonal pool)"
    },
    {
      "imageName": "S02E08_-_X_equals_Why-0082.jpg",
      "timestamp": "2025-09-14T20:34:22.493Z",
      "altText": "The Adventures of Pete & Pete - Season 2, Episode 8: X Equals Why",
      "episode": "S2E8",
      "season": 2,
      "episodeNumber": 8,
      "cycleInfo": "Post 3133 - 6775 available (16.6% excluded from seasonal pool)"
    },
    {
      "imageName": "S01E04_-_Rangeboy-0041.jpg",
      "timestamp": "2025-09-14T21:05:14.363Z",
      "altText": "The Adventures of Pete & Pete - Season 1, Episode 4: Rangeboy",
      "episode": "S1E4",
      "season": 1,
      "episodeNumber": 4,
      "cycleInfo": "Post 3134 - 6775 available (16.6% excluded from seasonal pool)"
    },
    {
      "imageName": "S02E05_-_Time_Tunnel-0126.jpg",
      "timestamp": "2025-09-14T21:34:19.712Z",
      "altText": "The Adventures of Pete & Pete - Season 2, Episode 5: Time Tunnel",
      "episode": "S2E5",
      "season": 2,
      "episodeNumber": 5,
      "cycleInfo": "Post 3135 - 6775 available (16.6% excluded from seasonal pool)"
    },
    {
      "imageName": "S03E03_-_The_Good,_the_Bad,_and_the_Lucky-0186.jpg",
      "timestamp": "2025-09-14T22:05:25.466Z",
      "altText": "The Adventures of Pete & Pete - Season 3, Episode 3: The Good, The Bad, and The Lucky",
      "episode": "S3E3",
      "season": 3,
      "episodeNumber": 3,
      "cycleInfo": "Post 3136 - 6775 available (16.6% excluded from seasonal pool)"
    },
    {
      "imageName": "S03E10_-_Pinned-0086.jpg",
      "timestamp": "2025-09-14T22:34:53.137Z",
      "altText": "The Adventures of Pete & Pete - Season 3, Episode 10: Pinned",
      "episode": "S3E10",
      "season": 3,
      "episodeNumber": 10,
      "cycleInfo": "Post 3137 - 6775 available (16.6% excluded from seasonal pool)"
    },
    {
      "imageName": "The_Adventures_of_Pete_&_Pete_-_0x26_-_StareMaster-0013.jpg",
      "timestamp": "2025-09-14T23:05:31.787Z",
      "altText": "The Adventures of Pete & Pete - Staremaster",
      "episode": "S0E26",
      "season": 0,
      "episodeNumber": 26,
      "cycleInfo": "Post 3138 - 6775 available (16.6% excluded from seasonal pool)"
    },
    {
      "imageName": "S03E02_-_The_Trouble_With_Teddy-0071.jpg",
      "timestamp": "2025-09-14T23:34:12.994Z",
      "altText": "The Adventures of Pete & Pete - Season 3, Episode 2: The Trouble With Teddy",
      "episode": "S3E2",
      "season": 3,
      "episodeNumber": 2,
      "cycleInfo": "Post 3139 - 6775 available (16.6% excluded from seasonal pool)"
    },
    {
      "imageName": "S02E12_-_Yellow_Fever-0151.jpg",
      "timestamp": "2025-09-15T00:26:26.955Z",
      "altText": "The Adventures of Pete & Pete - Season 2, Episode 12: Yellow Fever",
      "episode": "S2E12",
      "season": 2,
      "episodeNumber": 12,
      "cycleInfo": "Post 3140 - 6775 available (16.6% excluded from seasonal pool)"
    },
    {
      "imageName": "S03E04_-_Splashdown!-0204.jpg",
      "timestamp": "2025-09-15T00:51:14.155Z",
      "altText": "The Adventures of Pete & Pete - Season 3, Episode 4: Splashdown!",
      "episode": "S3E4",
      "season": 3,
      "episodeNumber": 4,
      "cycleInfo": "Post 3141 - 6775 available (16.6% excluded from seasonal pool)"
    },
    {
      "imageName": "S00E03_-_Space,_Geeks,_and_Johnny_Unitas-0204.jpg",
      "timestamp": "2025-09-15T01:34:32.837Z",
      "altText": "The Adventures of Pete & Pete - Space, Geeks, and Johnny Unitas",
      "episode": "S0E3",
      "season": 0,
      "episodeNumber": 3,
      "cycleInfo": "Post 3142 - 6775 available (16.6% excluded from seasonal pool)"
    },
    {
      "imageName": "S03E09_-_Road_Warrior-0072.jpg",
      "timestamp": "2025-09-15T02:35:23.000Z",
      "altText": "The Adventures of Pete & Pete - Season 3, Episode 9: Road Warrior",
      "episode": "S3E9",
      "season": 3,
      "episodeNumber": 9,
      "cycleInfo": "Post 3143 - 6775 available (16.6% excluded from seasonal pool)"
    },
    {
      "imageName": "S02E11_-_Farewell_My_Little_Viking_Part_2-0197.jpg",
      "timestamp": "2025-09-15T03:23:18.168Z",
      "altText": "The Adventures of Pete & Pete - Season 2, Episode 11: Farewell My Little Viking Part 2",
      "episode": "S2E11",
      "season": 2,
      "episodeNumber": 11,
      "cycleInfo": "Post 3144 - 6775 available (16.6% excluded from seasonal pool)"
    },
    {
      "imageName": "The_Adventures_of_Pete_&_Pete_-_0x01_-_What_Would_You_Do_for_a_Dollar-0004.jpg",
      "timestamp": "2025-09-15T03:44:19.704Z",
      "altText": "The Adventures of Pete & Pete - What Would You Do for a Dollar",
      "episode": "S0E1",
      "season": 0,
      "episodeNumber": 1,
      "cycleInfo": "Post 3145 - 6775 available (16.6% excluded from seasonal pool)"
    },
    {
      "imageName": "S03E13_-_Saturday-0180.jpg",
      "timestamp": "2025-09-15T04:07:23.550Z",
      "altText": "The Adventures of Pete & Pete - Season 3, Episode 13: Saturday",
      "episode": "S3E13",
      "season": 3,
      "episodeNumber": 13,
      "cycleInfo": "Post 3146 - 6775 available (16.6% excluded from seasonal pool)"
    },
    {
      "imageName": "S01E03_-_The_Nightcrawlers-0012.jpg",
      "timestamp": "2025-09-15T04:38:12.222Z",
      "altText": "The Adventures of Pete & Pete - Season 1, Episode 3: The Nightcrawlers",
      "episode": "S1E3",
      "season": 1,
      "episodeNumber": 3,
      "cycleInfo": "Post 3147 - 6775 available (16.6% excluded from seasonal pool)"
    },
    {
      "imageName": "S02E05_-_Time_Tunnel-0226.jpg",
      "timestamp": "2025-09-15T05:06:53.810Z",
      "altText": "The Adventures of Pete & Pete - Season 2, Episode 5: Time Tunnel",
      "episode": "S2E5",
      "season": 2,
      "episodeNumber": 5,
      "cycleInfo": "Post 3148 - 6775 available (16.6% excluded from seasonal pool)"
    },
    {
      "imageName": "S02E09_-_On_Golden_Pete-0011.jpg",
      "timestamp": "2025-09-15T05:36:56.406Z",
      "altText": "The Adventures of Pete & Pete - Season 2, Episode 9: On Golden Pete",
      "episode": "S2E9",
      "season": 2,
      "episodeNumber": 9,
      "cycleInfo": "Post 3149 - 6775 available (16.6% excluded from seasonal pool)"
    },
    {
      "imageName": "S02E11_-_Farewell_My_Little_Viking_Part_2-0112.jpg",
      "timestamp": "2025-09-15T06:09:49.850Z",
      "altText": "The Adventures of Pete & Pete - Season 2, Episode 11: Farewell My Little Viking Part 2",
      "episode": "S2E11",
      "season": 2,
      "episodeNumber": 11,
      "cycleInfo": "Post 3150 - 6775 available (16.6% excluded from seasonal pool)"
    },
    {
      "imageName": "S03E12_-_Das_Bus-0131.jpg",
      "timestamp": "2025-09-15T06:42:57.750Z",
      "altText": "The Adventures of Pete & Pete - Season 3, Episode 12: Das Bus",
      "episode": "S3E12",
      "season": 3,
      "episodeNumber": 12,
      "cycleInfo": "Post 3151 - 6775 available (16.6% excluded from seasonal pool)"
    },
    {
      "imageName": "S03E06_-_Crisis_in_the_Love_Zone-0122.jpg",
      "timestamp": "2025-09-15T07:07:15.834Z",
      "altText": "The Adventures of Pete & Pete - Season 3, Episode 6: Crisis in the Love Zone",
      "episode": "S3E6",
      "season": 3,
      "episodeNumber": 6,
      "cycleInfo": "Post 3152 - 6775 available (16.6% excluded from seasonal pool)"
    },
    {
      "imageName": "S01E06_-_Don't_Tread_on_Pete-0268.jpg",
      "timestamp": "2025-09-15T07:35:17.883Z",
      "altText": "The Adventures of Pete & Pete - Season 1, Episode 6: Don'T Tread on Pete",
      "episode": "S1E6",
      "season": 1,
      "episodeNumber": 6,
      "cycleInfo": "Post 3153 - 6775 available (16.6% excluded from seasonal pool)"
    },
    {
      "imageName": "S02E09_-_On_Golden_Pete-0097.jpg",
      "timestamp": "2025-09-15T08:08:47.095Z",
      "altText": "The Adventures of Pete & Pete - Season 2, Episode 9: On Golden Pete",
      "episode": "S2E9",
      "season": 2,
      "episodeNumber": 9,
      "cycleInfo": "Post 3154 - 6775 available (16.6% excluded from seasonal pool)"
    },
    {
      "imageName": "S01E07_-_When_Petes_Collide-0175.jpg",
      "timestamp": "2025-09-15T08:39:48.945Z",
      "altText": "The Adventures of Pete & Pete - Season 1, Episode 7: When Petes Collide",
      "episode": "S1E7",
      "season": 1,
      "episodeNumber": 7,
      "cycleInfo": "Post 3155 - 6775 available (16.6% excluded from seasonal pool)"
    },
    {
      "imageName": "S00E04_-_Apocalypse_Pete-0057.jpg",
      "timestamp": "2025-09-15T09:07:16.753Z",
      "altText": "The Adventures of Pete & Pete - Apocalypse Pete",
      "episode": "S0E4",
      "season": 0,
      "episodeNumber": 4,
      "cycleInfo": "Post 3156 - 6775 available (16.6% excluded from seasonal pool)"
    },
    {
      "imageName": "S02E11_-_Farewell_My_Little_Viking_Part_2-0138.jpg",
      "timestamp": "2025-09-15T09:37:00.125Z",
      "altText": "The Adventures of Pete & Pete - Season 2, Episode 11: Farewell My Little Viking Part 2",
      "episode": "S2E11",
      "season": 2,
      "episodeNumber": 11,
      "cycleInfo": "Post 3157 - 6775 available (16.6% excluded from seasonal pool)"
    },
    {
      "imageName": "S03E09_-_Road_Warrior-0279.jpg",
      "timestamp": "2025-09-15T10:07:10.990Z",
      "altText": "The Adventures of Pete & Pete - Season 3, Episode 9: Road Warrior",
      "episode": "S3E9",
      "season": 3,
      "episodeNumber": 9,
      "cycleInfo": "Post 3158 - 6775 available (16.6% excluded from seasonal pool)"
    },
    {
      "imageName": "S03E01_-_35_Hours-0207.jpg",
      "timestamp": "2025-09-15T10:37:58.216Z",
      "altText": "The Adventures of Pete & Pete - Season 3, Episode 1: 35 Hours",
      "episode": "S3E1",
      "season": 3,
      "episodeNumber": 1,
      "cycleInfo": "Post 3159 - 6775 available (16.6% excluded from seasonal pool)"
    },
    {
      "imageName": "The_Adventures_of_Pete_&_Pete_-_0x26_-_StareMaster-0023.jpg",
      "timestamp": "2025-09-15T11:05:35.137Z",
      "altText": "The Adventures of Pete & Pete - Staremaster",
      "episode": "S0E26",
      "season": 0,
      "episodeNumber": 26,
      "cycleInfo": "Post 3160 - 6775 available (16.6% excluded from seasonal pool)"
    },
    {
      "imageName": "S01E05_-_Tool_and_Die-0127.jpg",
      "timestamp": "2025-09-15T11:34:18.647Z",
      "altText": "The Adventures of Pete & Pete - Season 1, Episode 5: Tool and Die",
      "episode": "S1E5",
      "season": 1,
      "episodeNumber": 5,
      "cycleInfo": "Post 3161 - 6775 available (16.6% excluded from seasonal pool)"
    },
    {
      "imageName": "S02E09_-_On_Golden_Pete-0217.jpg",
      "timestamp": "2025-09-15T12:10:21.806Z",
      "altText": "The Adventures of Pete & Pete - Season 2, Episode 9: On Golden Pete",
      "episode": "S2E9",
      "season": 2,
      "episodeNumber": 9,
      "cycleInfo": "Post 3162 - 6775 available (16.6% excluded from seasonal pool)"
    },
    {
      "imageName": "S02E08_-_X_equals_Why-0198.jpg",
      "timestamp": "2025-09-15T12:47:13.987Z",
      "altText": "The Adventures of Pete & Pete - Season 2, Episode 8: X Equals Why",
      "episode": "S2E8",
      "season": 2,
      "episodeNumber": 8,
      "cycleInfo": "Post 3163 - 6775 available (16.6% excluded from seasonal pool)"
    },
    {
      "imageName": "S02E02_-_Field_of_Pete-0110.jpg",
      "timestamp": "2025-09-15T13:13:07.888Z",
      "altText": "The Adventures of Pete & Pete - Season 2, Episode 2: Field of Pete",
      "episode": "S2E2",
      "season": 2,
      "episodeNumber": 2,
      "cycleInfo": "Post 3164 - 6775 available (16.6% excluded from seasonal pool)"
    },
    {
      "imageName": "S03E07_-_Last_Laugh-0155.jpg",
      "timestamp": "2025-09-15T13:37:33.113Z",
      "altText": "The Adventures of Pete & Pete - Season 3, Episode 7: Last Laugh",
      "episode": "S3E7",
      "season": 3,
      "episodeNumber": 7,
      "cycleInfo": "Post 3165 - 6775 available (16.6% excluded from seasonal pool)"
    },
    {
      "imageName": "S01E02_-_Day_of_The_Dot-0140.jpg",
      "timestamp": "2025-09-15T14:06:49.775Z",
      "altText": "The Adventures of Pete & Pete - Season 1, Episode 2: Day of the Dot",
      "episode": "S1E2",
      "season": 1,
      "episodeNumber": 2,
      "cycleInfo": "Post 3166 - 6775 available (16.6% excluded from seasonal pool)"
    },
    {
      "imageName": "S02E09_-_On_Golden_Pete-0060.jpg",
      "timestamp": "2025-09-15T14:37:12.410Z",
      "altText": "The Adventures of Pete & Pete - Season 2, Episode 9: On Golden Pete",
      "episode": "S2E9",
      "season": 2,
      "episodeNumber": 9,
      "cycleInfo": "Post 3167 - 6775 available (16.6% excluded from seasonal pool)"
    },
    {
      "imageName": "S00E02_-_What_We_Did_on_Our_Summer_Vacation-0067.jpg",
      "timestamp": "2025-09-15T15:06:50.257Z",
      "altText": "The Adventures of Pete & Pete - What We Did on Our Summer Vacation",
      "episode": "S0E2",
      "season": 0,
      "episodeNumber": 2,
      "cycleInfo": "Post 3168 - 6775 available (16.6% excluded from seasonal pool)"
    }
  ],
  "lastUpdated": "2025-09-15T15:06:50.257Z"
}