{
  "entries": [
    {
      "imageName": "S01E08_-_Hard_Day's_Pete-0164.jpg",
      "timestamp": "2025-11-12T20:38:07.947Z",
      "altText": "The Adventures of Pete & Pete - Season 1, Episode 8: Hard Day'S Pete",
      "episode": "S1E8",
      "season": 1,
      "episodeNumber": 8,
      "cycleInfo": "Post 677 - 7443 available (8.3% excluded from seasonal pool)"
    },
    {
      "imageName": "S01E03_-_The_Nightcrawlers-0160.jpg",
      "timestamp": "2025-11-12T21:06:20.584Z",
      "altText": "The Adventures of Pete & Pete - Season 1, Episode 3: The Nightcrawlers",
      "episode": "S1E3",
      "season": 1,
      "episodeNumber": 3,
      "cycleInfo": "Post 678 - 7442 available (8.3% excluded from seasonal pool)"
    },
    {
      "imageName": "S02E13_-_Sick_Day-0053.jpg",
      "timestamp": "2025-11-12T21:35:37.477Z",
      "altText": "The Adventures of Pete & Pete - Season 2, Episode 13: Sick Day",
      "episode": "S2E13",
      "season": 2,
      "episodeNumber": 13,
      "cycleInfo": "Post 679 - 7441 available (8.4% excluded from seasonal pool)"
    },
    {
      "imageName": "S01E07_-_When_Petes_Collide-0040.jpg",
      "timestamp": "2025-11-12T22:06:50.762Z",
      "altText": "The Adventures of Pete & Pete - Season 1, Episode 7: When Petes Collide",
      "episode": "S1E7",
      "season": 1,
      "episodeNumber": 7,
      "cycleInfo": "Post 680 - 7440 available (8.4% excluded from seasonal pool)"
    },
    {
      "imageName": "S02E09_-_On_Golden_Pete-0195.jpg",
      "timestamp": "2025-11-12T22:35:48.432Z",
      "altText": "The Adventures of Pete & Pete - Season 2, Episode 9: On Golden Pete",
      "episode": "S2E9",
      "season": 2,
      "episodeNumber": 9,
      "cycleInfo": "Post 681 - 7439 available (8.4% excluded from seasonal pool)"
    },
    {
      "imageName": "S03E02_-_The_Trouble_With_Teddy-0161.jpg",
      "timestamp": "2025-11-12T23:06:32.447Z",
      "altText": "The Adventures of Pete & Pete - Season 3, Episode 2: The Trouble With Teddy",
      "episode": "S3E2",
      "season": 3,
      "episodeNumber": 2,
      "cycleInfo": "Post 682 - 7438 available (8.4% excluded from seasonal pool)"
    },
    {
      "imageName": "S01E03_-_The_Nightcrawlers-0067.jpg",
      "timestamp": "2025-11-12T23:35:11.721Z",
      "altText": "The Adventures of Pete & Pete - Season 1, Episode 3: The Nightcrawlers",
      "episode": "S1E3",
      "season": 1,
      "episodeNumber": 3,
      "cycleInfo": "Post 683 - 7437 available (8.4% excluded from seasonal pool)"
    },
    {
      "imageName": "S02E11_-_Farewell_My_Little_Viking_Part_2-0076.jpg",
      "timestamp": "2025-11-13T00:26:10.900Z",
      "altText": "The Adventures of Pete & Pete - Season 2, Episode 11: Farewell My Little Viking Part 2",
      "episode": "S2E11",
      "season": 2,
      "episodeNumber": 11,
      "cycleInfo": "Post 684 - 7436 available (8.4% excluded from seasonal pool)"
    },
    {
      "imageName": "S02E12_-_Yellow_Fever-0078.jpg",
      "timestamp": "2025-11-13T00:51:07.295Z",
      "altText": "The Adventures of Pete & Pete - Season 2, Episode 12: Yellow Fever",
      "episode": "S2E12",
      "season": 2,
      "episodeNumber": 12,
      "cycleInfo": "Post 685 - 7435 available (8.4% excluded from seasonal pool)"
    },
    {
      "imageName": "S02E05_-_Time_Tunnel-0215.jpg",
      "timestamp": "2025-11-13T01:34:41.286Z",
      "altText": "The Adventures of Pete & Pete - Season 2, Episode 5: Time Tunnel",
      "episode": "S2E5",
      "season": 2,
      "episodeNumber": 5,
      "cycleInfo": "Post 686 - 7434 available (8.4% excluded from seasonal pool)"
    },
    {
      "imageName": "S03E03_-_The_Good,_the_Bad,_and_the_Lucky-0159.jpg",
      "timestamp": "2025-11-13T02:37:36.290Z",
      "altText": "The Adventures of Pete & Pete - Season 3, Episode 3: The Good, The Bad, and The Lucky",
      "episode": "S3E3",
      "season": 3,
      "episodeNumber": 3,
      "cycleInfo": "Post 687 - 7433 available (8.5% excluded from seasonal pool)"
    },
    {
      "imageName": "S02E09_-_On_Golden_Pete-0009.jpg",
      "timestamp": "2025-11-13T03:27:23.588Z",
      "altText": "The Adventures of Pete & Pete - Season 2, Episode 9: On Golden Pete",
      "episode": "S2E9",
      "season": 2,
      "episodeNumber": 9,
      "cycleInfo": "Post 688 - 7432 available (8.5% excluded from seasonal pool)"
    },
    {
      "imageName": "S02E07_-_Inspector_34-0086.jpg",
      "timestamp": "2025-11-13T03:49:27.284Z",
      "altText": "The Adventures of Pete & Pete - Season 2, Episode 7: Inspector 34",
      "episode": "S2E7",
      "season": 2,
      "episodeNumber": 7,
      "cycleInfo": "Post 689 - 7431 available (8.5% excluded from seasonal pool)"
    },
    {
      "imageName": "S01E05_-_Tool_and_Die-0064.jpg",
      "timestamp": "2025-11-13T04:10:33.287Z",
      "altText": "The Adventures of Pete & Pete - Season 1, Episode 5: Tool and Die",
      "episode": "S1E5",
      "season": 1,
      "episodeNumber": 5,
      "cycleInfo": "Post 690 - 7430 available (8.5% excluded from seasonal pool)"
    },
    {
      "imageName": "S01E03_-_The_Nightcrawlers-0128.jpg",
      "timestamp": "2025-11-13T04:40:21.812Z",
      "altText": "The Adventures of Pete & Pete - Season 1, Episode 3: The Nightcrawlers",
      "episode": "S1E3",
      "season": 1,
      "episodeNumber": 3,
      "cycleInfo": "Post 691 - 7429 available (8.5% excluded from seasonal pool)"
    },
    {
      "imageName": "S02E05_-_Time_Tunnel-0102.jpg",
      "timestamp": "2025-11-13T05:06:54.339Z",
      "altText": "The Adventures of Pete & Pete - Season 2, Episode 5: Time Tunnel",
      "episode": "S2E5",
      "season": 2,
      "episodeNumber": 5,
      "cycleInfo": "Post 692 - 7428 available (8.5% excluded from seasonal pool)"
    },
    {
      "imageName": "S01E01_-_King_of_The_Road-0089.jpg",
      "timestamp": "2025-11-13T05:37:57.477Z",
      "altText": "The Adventures of Pete & Pete - Season 1, Episode 1: King of the Road",
      "episode": "S1E1",
      "season": 1,
      "episodeNumber": 1,
      "cycleInfo": "Post 693 - 7427 available (8.5% excluded from seasonal pool)"
    },
    {
      "imageName": "S03E10_-_Pinned-0093.jpg",
      "timestamp": "2025-11-13T06:09:40.701Z",
      "altText": "The Adventures of Pete & Pete - Season 3, Episode 10: Pinned",
      "episode": "S3E10",
      "season": 3,
      "episodeNumber": 10,
      "cycleInfo": "Post 694 - 7426 available (8.5% excluded from seasonal pool)"
    },
    {
      "imageName": "S02E12_-_Yellow_Fever-0207.jpg",
      "timestamp": "2025-11-13T06:43:40.098Z",
      "altText": "The Adventures of Pete & Pete - Season 2, Episode 12: Yellow Fever",
      "episode": "S2E12",
      "season": 2,
      "episodeNumber": 12,
      "cycleInfo": "Post 695 - 7425 available (8.6% excluded from seasonal pool)"
    },
    {
      "imageName": "S03E09_-_Road_Warrior-0154.jpg",
      "timestamp": "2025-11-13T07:07:07.314Z",
      "altText": "The Adventures of Pete & Pete - Season 3, Episode 9: Road Warrior",
      "episode": "S3E9",
      "season": 3,
      "episodeNumber": 9,
      "cycleInfo": "Post 696 - 7424 available (8.6% excluded from seasonal pool)"
    },
    {
      "imageName": "S03E04_-_Splashdown!-0078.jpg",
      "timestamp": "2025-11-13T07:35:56.920Z",
      "altText": "The Adventures of Pete & Pete - Season 3, Episode 4: Splashdown!",
      "episode": "S3E4",
      "season": 3,
      "episodeNumber": 4,
      "cycleInfo": "Post 697 - 7423 available (8.6% excluded from seasonal pool)"
    },
    {
      "imageName": "S03E12_-_Das_Bus-0270.jpg",
      "timestamp": "2025-11-13T08:08:27.940Z",
      "altText": "The Adventures of Pete & Pete - Season 3, Episode 12: Das Bus",
      "episode": "S3E12",
      "season": 3,
      "episodeNumber": 12,
      "cycleInfo": "Post 698 - 7422 available (8.6% excluded from seasonal pool)"
    },
    {
      "imageName": "S01E04_-_Rangeboy-0111.jpg",
      "timestamp": "2025-11-13T08:41:14.338Z",
      "altText": "The Adventures of Pete & Pete - Season 1, Episode 4: Rangeboy",
      "episode": "S1E4",
      "season": 1,
      "episodeNumber": 4,
      "cycleInfo": "Post 699 - 7421 available (8.6% excluded from seasonal pool)"
    },
    {
      "imageName": "S02E08_-_X_equals_Why-0139.jpg",
      "timestamp": "2025-11-13T09:07:19.484Z",
      "altText": "The Adventures of Pete & Pete - Season 2, Episode 8: X Equals Why",
      "episode": "S2E8",
      "season": 2,
      "episodeNumber": 8,
      "cycleInfo": "Post 700 - 7420 available (8.6% excluded from seasonal pool)"
    },
    {
      "imageName": "S03E05_-_Dance_Fever-0144.jpg",
      "timestamp": "2025-11-13T09:37:48.325Z",
      "altText": "The Adventures of Pete & Pete - Season 3, Episode 5: Dance Fever",
      "episode": "S3E5",
      "season": 3,
      "episodeNumber": 5,
      "cycleInfo": "Post 701 - 7419 available (8.6% excluded from seasonal pool)"
    },
    {
      "imageName": "S02E11_-_Farewell_My_Little_Viking_Part_2-0140.jpg",
      "timestamp": "2025-11-13T10:07:31.831Z",
      "altText": "The Adventures of Pete & Pete - Season 2, Episode 11: Farewell My Little Viking Part 2",
      "episode": "S2E11",
      "season": 2,
      "episodeNumber": 11,
      "cycleInfo": "Post 702 - 7418 available (8.6% excluded from seasonal pool)"
    },
    {
      "imageName": "S03E07_-_Last_Laugh-0106.jpg",
      "timestamp": "2025-11-13T10:40:05.076Z",
      "altText": "The Adventures of Pete & Pete - Season 3, Episode 7: Last Laugh",
      "episode": "S3E7",
      "season": 3,
      "episodeNumber": 7,
      "cycleInfo": "Post 703 - 7417 available (8.7% excluded from seasonal pool)"
    },
    {
      "imageName": "S03E04_-_Splashdown!-0197.jpg",
      "timestamp": "2025-11-13T11:05:59.417Z",
      "altText": "The Adventures of Pete & Pete - Season 3, Episode 4: Splashdown!",
      "episode": "S3E4",
      "season": 3,
      "episodeNumber": 4,
      "cycleInfo": "Post 704 - 7416 available (8.7% excluded from seasonal pool)"
    },
    {
      "imageName": "S01E02_-_Day_of_The_Dot-0118.jpg",
      "timestamp": "2025-11-13T11:35:08.165Z",
      "altText": "The Adventures of Pete & Pete - Season 1, Episode 2: Day of the Dot",
      "episode": "S1E2",
      "season": 1,
      "episodeNumber": 2,
      "cycleInfo": "Post 705 - 7415 available (8.7% excluded from seasonal pool)"
    },
    {
      "imageName": "S02E01_-_Grounded_For_Life-0160.jpg",
      "timestamp": "2025-11-13T12:10:50.229Z",
      "altText": "The Adventures of Pete & Pete - Season 2, Episode 1: Grounded for Life",
      "episode": "S2E1",
      "season": 2,
      "episodeNumber": 1,
      "cycleInfo": "Post 706 - 7414 available (8.7% excluded from seasonal pool)"
    },
    {
      "imageName": "S03E09_-_Road_Warrior-0037.jpg",
      "timestamp": "2025-11-13T12:47:27.991Z",
      "altText": "The Adventures of Pete & Pete - Season 3, Episode 9: Road Warrior",
      "episode": "S3E9",
      "season": 3,
      "episodeNumber": 9,
      "cycleInfo": "Post 707 - 7413 available (8.7% excluded from seasonal pool)"
    },
    {
      "imageName": "S02E10_-_Farewell_My_Little_Viking_Part_1-0014.jpg",
      "timestamp": "2025-11-13T13:16:13.992Z",
      "altText": "The Adventures of Pete & Pete - Season 2, Episode 10: Farewell My Little Viking Part 1",
      "episode": "S2E10",
      "season": 2,
      "episodeNumber": 10,
      "cycleInfo": "Post 708 - 7412 available (8.7% excluded from seasonal pool)"
    },
    {
      "imageName": "S00E02_-_What_We_Did_on_Our_Summer_Vacation-0201.jpg",
      "timestamp": "2025-11-13T13:43:24.815Z",
      "altText": "The Adventures of Pete & Pete - What We Did on Our Summer Vacation",
      "episode": "S0E2",
      "season": 0,
      "episodeNumber": 2,
      "cycleInfo": "Post 709 - 7411 available (8.7% excluded from seasonal pool)"
    },
    {
      "imageName": "S02E01_-_Grounded_For_Life-0001.jpg",
      "timestamp": "2025-11-13T14:07:11.463Z",
      "altText": "The Adventures of Pete & Pete - Season 2, Episode 1: Grounded for Life",
      "episode": "S2E1",
      "season": 2,
      "episodeNumber": 1,
      "cycleInfo": "Post 710 - 7410 available (8.7% excluded from seasonal pool)"
    },
    {
      "imageName": "S02E08_-_X_equals_Why-0158.jpg",
      "timestamp": "2025-11-13T14:36:41.836Z",
      "altText": "The Adventures of Pete & Pete - Season 2, Episode 8: X Equals Why",
      "episode": "S2E8",
      "season": 2,
      "episodeNumber": 8,
      "cycleInfo": "Post 711 - 7409 available (8.8% excluded from seasonal pool)"
    },
    {
      "imageName": "S03E13_-_Saturday-0167.jpg",
      "timestamp": "2025-11-13T15:07:37.818Z",
      "altText": "The Adventures of Pete & Pete - Season 3, Episode 13: Saturday",
      "episode": "S3E13",
      "season": 3,
      "episodeNumber": 13,
      "cycleInfo": "Post 712 - 7408 available (8.8% excluded from seasonal pool)"
    },
    {
      "imageName": "S02E03_-_The_Call-0077.jpg",
      "timestamp": "2025-11-13T15:36:44.061Z",
      "altText": "The Adventures of Pete & Pete - Season 2, Episode 3: The Call",
      "episode": "S2E3",
      "season": 2,
      "episodeNumber": 3,
      "cycleInfo": "Post 713 - 7407 available (8.8% excluded from seasonal pool)"
    },
    {
      "imageName": "S02E12_-_Yellow_Fever-0282.jpg",
      "timestamp": "2025-11-13T16:07:53.991Z",
      "altText": "The Adventures of Pete & Pete - Season 2, Episode 12: Yellow Fever",
      "episode": "S2E12",
      "season": 2,
      "episodeNumber": 12,
      "cycleInfo": "Post 714 - 7406 available (8.8% excluded from seasonal pool)"
    },
    {
      "imageName": "S02E01_-_Grounded_For_Life-0170.jpg",
      "timestamp": "2025-11-13T16:41:25.181Z",
      "altText": "The Adventures of Pete & Pete - Season 2, Episode 1: Grounded for Life",
      "episode": "S2E1",
      "season": 2,
      "episodeNumber": 1,
      "cycleInfo": "Post 715 - 7405 available (8.8% excluded from seasonal pool)"
    },
    {
      "imageName": "S02E10_-_Farewell_My_Little_Viking_Part_1-0179.jpg",
      "timestamp": "2025-11-13T17:07:11.257Z",
      "altText": "The Adventures of Pete & Pete - Season 2, Episode 10: Farewell My Little Viking Part 1",
      "episode": "S2E10",
      "season": 2,
      "episodeNumber": 10,
      "cycleInfo": "Post 716 - 7404 available (8.8% excluded from seasonal pool)"
    },
    {
      "imageName": "The_Adventures_of_Pete_&_Pete_-_0x26_-_StareMaster-0008.jpg",
      "timestamp": "2025-11-13T17:37:30.563Z",
      "altText": "The Adventures of Pete & Pete - Staremaster",
      "episode": "S0E26",
      "season": 0,
      "episodeNumber": 26,
      "cycleInfo": "Post 717 - 7403 available (8.8% excluded from seasonal pool)"
    },
    {
      "imageName": "S02E08_-_X_equals_Why-0121.jpg",
      "timestamp": "2025-11-13T18:08:10.835Z",
      "altText": "The Adventures of Pete & Pete - Season 2, Episode 8: X Equals Why",
      "episode": "S2E8",
      "season": 2,
      "episodeNumber": 8,
      "cycleInfo": "Post 718 - 7402 available (8.8% excluded from seasonal pool)"
    },
    {
      "imageName": "S01E07_-_When_Petes_Collide-0276.jpg",
      "timestamp": "2025-11-13T18:42:20.973Z",
      "altText": "The Adventures of Pete & Pete - Season 1, Episode 7: When Petes Collide",
      "episode": "S1E7",
      "season": 1,
      "episodeNumber": 7,
      "cycleInfo": "Post 719 - 7401 available (8.9% excluded from seasonal pool)"
    },
    {
      "imageName": "S02E09_-_On_Golden_Pete-0049.jpg",
      "timestamp": "2025-11-13T19:05:23.609Z",
      "altText": "The Adventures of Pete & Pete - Season 2, Episode 9: On Golden Pete",
      "episode": "S2E9",
      "season": 2,
      "episodeNumber": 9,
      "cycleInfo": "Post 720 - 7400 available (8.9% excluded from seasonal pool)"
    },
    {
      "imageName": "S02E03_-_The_Call-0165.jpg",
      "timestamp": "2025-11-13T19:34:07.274Z",
      "altText": "The Adventures of Pete & Pete - Season 2, Episode 3: The Call",
      "episode": "S2E3",
      "season": 2,
      "episodeNumber": 3,
      "cycleInfo": "Post 721 - 7399 available (8.9% excluded from seasonal pool)"
    },
    {
      "imageName": "S02E11_-_Farewell_My_Little_Viking_Part_2-0251.jpg",
      "timestamp": "2025-11-13T20:07:22.910Z",
      "altText": "The Adventures of Pete & Pete - Season 2, Episode 11: Farewell My Little Viking Part 2",
      "episode": "S2E11",
      "season": 2,
      "episodeNumber": 11,
      "cycleInfo": "Post 722 - 7398 available (8.9% excluded from seasonal pool)"
    },
    {
      "imageName": "S03E07_-_Last_Laugh-0122.jpg",
      "timestamp": "2025-11-13T20:37:39.590Z",
      "altText": "The Adventures of Pete & Pete - Season 3, Episode 7: Last Laugh",
      "episode": "S3E7",
      "season": 3,
      "episodeNumber": 7,
      "cycleInfo": "Post 723 - 7397 available (8.9% excluded from seasonal pool)"
    },
    {
      "imageName": "S03E10_-_Pinned-0084.jpg",
      "timestamp": "2025-11-13T21:06:28.871Z",
      "altText": "The Adventures of Pete & Pete - Season 3, Episode 10: Pinned",
      "episode": "S3E10",
      "season": 3,
      "episodeNumber": 10,
      "cycleInfo": "Post 724 - 7396 available (8.9% excluded from seasonal pool)"
    },
    {
      "imageName": "S02E09_-_On_Golden_Pete-0288.jpg",
      "timestamp": "2025-11-13T21:34:06.088Z",
      "altText": "The Adventures of Pete & Pete - Season 2, Episode 9: On Golden Pete",
      "episode": "S2E9",
      "season": 2,
      "episodeNumber": 9,
      "cycleInfo": "Post 725 - 7395 available (8.9% excluded from seasonal pool)"
    },
    {
      "imageName": "S03E05_-_Dance_Fever-0173.jpg",
      "timestamp": "2025-11-13T22:06:57.950Z",
      "altText": "The Adventures of Pete & Pete - Season 3, Episode 5: Dance Fever",
      "episode": "S3E5",
      "season": 3,
      "episodeNumber": 5,
      "cycleInfo": "Post 726 - 7394 available (8.9% excluded from seasonal pool)"
    },
    {
      "imageName": "The_Adventures_of_Pete_&_Pete_-_0x09_-_Flossing-0002.jpg",
      "timestamp": "2025-11-13T22:36:55.631Z",
      "altText": "The Adventures of Pete & Pete - Flossing",
      "episode": "S0E9",
      "season": 0,
      "episodeNumber": 9,
      "cycleInfo": "Post 727 - 7393 available (9.0% excluded from seasonal pool)"
    },
    {
      "imageName": "S02E03_-_The_Call-0020.jpg",
      "timestamp": "2025-11-13T23:06:41.153Z",
      "altText": "The Adventures of Pete & Pete - Season 2, Episode 3: The Call",
      "episode": "S2E3",
      "season": 2,
      "episodeNumber": 3,
      "cycleInfo": "Post 728 - 7392 available (9.0% excluded from seasonal pool)"
    },
    {
      "imageName": "S01E07_-_When_Petes_Collide-0093.jpg",
      "timestamp": "2025-11-13T23:34:55.573Z",
      "altText": "The Adventures of Pete & Pete - Season 1, Episode 7: When Petes Collide",
      "episode": "S1E7",
      "season": 1,
      "episodeNumber": 7,
      "cycleInfo": "Post 729 - 7391 available (9.0% excluded from seasonal pool)"
    },
    {
      "imageName": "S03E06_-_Crisis_in_the_Love_Zone-0066.jpg",
      "timestamp": "2025-11-14T00:26:59.696Z",
      "altText": "The Adventures of Pete & Pete - Season 3, Episode 6: Crisis in the Love Zone",
      "episode": "S3E6",
      "season": 3,
      "episodeNumber": 6,
      "cycleInfo": "Post 730 - 7390 available (9.0% excluded from seasonal pool)"
    },
    {
      "imageName": "S03E10_-_Pinned-0125.jpg",
      "timestamp": "2025-11-14T00:51:59.647Z",
      "altText": "The Adventures of Pete & Pete - Season 3, Episode 10: Pinned",
      "episode": "S3E10",
      "season": 3,
      "episodeNumber": 10,
      "cycleInfo": "Post 731 - 7389 available (9.0% excluded from seasonal pool)"
    },
    {
      "imageName": "S02E09_-_On_Golden_Pete-0272.jpg",
      "timestamp": "2025-11-14T01:34:22.759Z",
      "altText": "The Adventures of Pete & Pete - Season 2, Episode 9: On Golden Pete",
      "episode": "S2E9",
      "season": 2,
      "episodeNumber": 9,
      "cycleInfo": "Post 732 - 7388 available (9.0% excluded from seasonal pool)"
    },
    {
      "imageName": "S03E01_-_35_Hours-0247.jpg",
      "timestamp": "2025-11-14T02:36:49.122Z",
      "altText": "The Adventures of Pete & Pete - Season 3, Episode 1: 35 Hours",
      "episode": "S3E1",
      "season": 3,
      "episodeNumber": 1,
      "cycleInfo": "Post 733 - 7387 available (9.0% excluded from seasonal pool)"
    },
    {
      "imageName": "S01E06_-_Don't_Tread_on_Pete-0076.jpg",
      "timestamp": "2025-11-14T03:26:31.301Z",
      "altText": "The Adventures of Pete & Pete - Season 1, Episode 6: Don'T Tread on Pete",
      "episode": "S1E6",
      "season": 1,
      "episodeNumber": 6,
      "cycleInfo": "Post 734 - 7386 available (9.0% excluded from seasonal pool)"
    },
    {
      "imageName": "S01E07_-_When_Petes_Collide-0244.jpg",
      "timestamp": "2025-11-14T03:48:04.057Z",
      "altText": "The Adventures of Pete & Pete - Season 1, Episode 7: When Petes Collide",
      "episode": "S1E7",
      "season": 1,
      "episodeNumber": 7,
      "cycleInfo": "Post 735 - 7385 available (9.1% excluded from seasonal pool)"
    },
    {
      "imageName": "S03E09_-_Road_Warrior-0198.jpg",
      "timestamp": "2025-11-14T04:08:43.671Z",
      "altText": "The Adventures of Pete & Pete - Season 3, Episode 9: Road Warrior",
      "episode": "S3E9",
      "season": 3,
      "episodeNumber": 9,
      "cycleInfo": "Post 736 - 7384 available (9.1% excluded from seasonal pool)"
    },
    {
      "imageName": "S03E08_-_Allnighter-0098.jpg",
      "timestamp": "2025-11-14T04:39:21.958Z",
      "altText": "The Adventures of Pete & Pete - Season 3, Episode 8: Allnighter",
      "episode": "S3E8",
      "season": 3,
      "episodeNumber": 8,
      "cycleInfo": "Post 737 - 7383 available (9.1% excluded from seasonal pool)"
    },
    {
      "imageName": "S01E03_-_The_Nightcrawlers-0090.jpg",
      "timestamp": "2025-11-14T05:06:47.447Z",
      "altText": "The Adventures of Pete & Pete - Season 1, Episode 3: The Nightcrawlers",
      "episode": "S1E3",
      "season": 1,
      "episodeNumber": 3,
      "cycleInfo": "Post 738 - 7382 available (9.1% excluded from seasonal pool)"
    },
    {
      "imageName": "S03E02_-_The_Trouble_With_Teddy-0218.jpg",
      "timestamp": "2025-11-14T05:37:23.643Z",
      "altText": "The Adventures of Pete & Pete - Season 3, Episode 2: The Trouble With Teddy",
      "episode": "S3E2",
      "season": 3,
      "episodeNumber": 2,
      "cycleInfo": "Post 739 - 7381 available (9.1% excluded from seasonal pool)"
    },
    {
      "imageName": "S03E04_-_Splashdown!-0070.jpg",
      "timestamp": "2025-11-14T06:09:43.074Z",
      "altText": "The Adventures of Pete & Pete - Season 3, Episode 4: Splashdown!",
      "episode": "S3E4",
      "season": 3,
      "episodeNumber": 4,
      "cycleInfo": "Post 740 - 7380 available (9.1% excluded from seasonal pool)"
    },
    {
      "imageName": "S01E06_-_Don't_Tread_on_Pete-0241.jpg",
      "timestamp": "2025-11-14T06:43:35.754Z",
      "altText": "The Adventures of Pete & Pete - Season 1, Episode 6: Don'T Tread on Pete",
      "episode": "S1E6",
      "season": 1,
      "episodeNumber": 6,
      "cycleInfo": "Post 741 - 7379 available (9.1% excluded from seasonal pool)"
    },
    {
      "imageName": "S01E05_-_Tool_and_Die-0128.jpg",
      "timestamp": "2025-11-14T07:07:02.658Z",
      "altText": "The Adventures of Pete & Pete - Season 1, Episode 5: Tool and Die",
      "episode": "S1E5",
      "season": 1,
      "episodeNumber": 5,
      "cycleInfo": "Post 742 - 7378 available (9.1% excluded from seasonal pool)"
    },
    {
      "imageName": "S02E12_-_Yellow_Fever-0136.jpg",
      "timestamp": "2025-11-14T07:35:18.546Z",
      "altText": "The Adventures of Pete & Pete - Season 2, Episode 12: Yellow Fever",
      "episode": "S2E12",
      "season": 2,
      "episodeNumber": 12,
      "cycleInfo": "Post 743 - 7377 available (9.2% excluded from seasonal pool)"
    },
    {
      "imageName": "S03E12_-_Das_Bus-0126.jpg",
      "timestamp": "2025-11-14T08:08:45.961Z",
      "altText": "The Adventures of Pete & Pete - Season 3, Episode 12: Das Bus",
      "episode": "S3E12",
      "season": 3,
      "episodeNumber": 12,
      "cycleInfo": "Post 744 - 7376 available (9.2% excluded from seasonal pool)"
    },
    {
      "imageName": "The_Adventures_of_Pete_&_Pete_-_0x20_-_The_Punishment-0005.jpg",
      "timestamp": "2025-11-14T08:40:12.488Z",
      "altText": "The Adventures of Pete & Pete - The Punishment",
      "episode": "S0E20",
      "season": 0,
      "episodeNumber": 20,
      "cycleInfo": "Post 745 - 7375 available (9.2% excluded from seasonal pool)"
    },
    {
      "imageName": "S01E01_-_King_of_The_Road-0165.jpg",
      "timestamp": "2025-11-14T09:07:05.397Z",
      "altText": "The Adventures of Pete & Pete - Season 1, Episode 1: King of the Road",
      "episode": "S1E1",
      "season": 1,
      "episodeNumber": 1,
      "cycleInfo": "Post 746 - 7374 available (9.2% excluded from seasonal pool)"
    },
    {
      "imageName": "S00E04_-_Apocalypse_Pete-0069.jpg",
      "timestamp": "2025-11-14T09:37:23.124Z",
      "altText": "The Adventures of Pete & Pete - Apocalypse Pete",
      "episode": "S0E4",
      "season": 0,
      "episodeNumber": 4,
      "cycleInfo": "Post 747 - 7373 available (9.2% excluded from seasonal pool)"
    },
    {
      "imageName": "S02E07_-_Inspector_34-0157.jpg",
      "timestamp": "2025-11-14T10:07:30.326Z",
      "altText": "The Adventures of Pete & Pete - Season 2, Episode 7: Inspector 34",
      "episode": "S2E7",
      "season": 2,
      "episodeNumber": 7,
      "cycleInfo": "Post 748 - 7372 available (9.2% excluded from seasonal pool)"
    },
    {
      "imageName": "S03E05_-_Dance_Fever-0050.jpg",
      "timestamp": "2025-11-14T10:39:07.573Z",
      "altText": "The Adventures of Pete & Pete - Season 3, Episode 5: Dance Fever",
      "episode": "S3E5",
      "season": 3,
      "episodeNumber": 5,
      "cycleInfo": "Post 749 - 7371 available (9.2% excluded from seasonal pool)"
    },
    {
      "imageName": "S01E07_-_When_Petes_Collide-0037.jpg",
      "timestamp": "2025-11-14T11:05:40.771Z",
      "altText": "The Adventures of Pete & Pete - Season 1, Episode 7: When Petes Collide",
      "episode": "S1E7",
      "season": 1,
      "episodeNumber": 7,
      "cycleInfo": "Post 750 - 7370 available (9.2% excluded from seasonal pool)"
    },
    {
      "imageName": "S01E06_-_Don't_Tread_on_Pete-0014.jpg",
      "timestamp": "2025-11-14T11:34:46.360Z",
      "altText": "The Adventures of Pete & Pete - Season 1, Episode 6: Don'T Tread on Pete",
      "episode": "S1E6",
      "season": 1,
      "episodeNumber": 6,
      "cycleInfo": "Post 751 - 7369 available (9.2% excluded from seasonal pool)"
    },
    {
      "imageName": "S03E01_-_35_Hours-0114.jpg",
      "timestamp": "2025-11-14T12:10:48.608Z",
      "altText": "The Adventures of Pete & Pete - Season 3, Episode 1: 35 Hours",
      "episode": "S3E1",
      "season": 3,
      "episodeNumber": 1,
      "cycleInfo": "Post 752 - 7368 available (9.3% excluded from seasonal pool)"
    },
    {
      "imageName": "S03E02_-_The_Trouble_With_Teddy-0203.jpg",
      "timestamp": "2025-11-14T12:47:18.592Z",
      "altText": "The Adventures of Pete & Pete - Season 3, Episode 2: The Trouble With Teddy",
      "episode": "S3E2",
      "season": 3,
      "episodeNumber": 2,
      "cycleInfo": "Post 753 - 7367 available (9.3% excluded from seasonal pool)"
    },
    {
      "imageName": "S02E10_-_Farewell_My_Little_Viking_Part_1-0156.jpg",
      "timestamp": "2025-11-14T13:14:10.394Z",
      "altText": "The Adventures of Pete & Pete - Season 2, Episode 10: Farewell My Little Viking Part 1",
      "episode": "S2E10",
      "season": 2,
      "episodeNumber": 10,
      "cycleInfo": "Post 754 - 7366 available (9.3% excluded from seasonal pool)"
    },
    {
      "imageName": "S00E02_-_What_We_Did_on_Our_Summer_Vacation-0104.jpg",
      "timestamp": "2025-11-14T13:40:56.264Z",
      "altText": "The Adventures of Pete & Pete - What We Did on Our Summer Vacation",
      "episode": "S0E2",
      "season": 0,
      "episodeNumber": 2,
      "cycleInfo": "Post 755 - 7365 available (9.3% excluded from seasonal pool)"
    },
    {
      "imageName": "S02E12_-_Yellow_Fever-0063.jpg",
      "timestamp": "2025-11-14T14:06:37.396Z",
      "altText": "The Adventures of Pete & Pete - Season 2, Episode 12: Yellow Fever",
      "episode": "S2E12",
      "season": 2,
      "episodeNumber": 12,
      "cycleInfo": "Post 756 - 7364 available (9.3% excluded from seasonal pool)"
    },
    {
      "imageName": "S03E04_-_Splashdown!-0065.jpg",
      "timestamp": "2025-11-14T14:37:13.244Z",
      "altText": "The Adventures of Pete & Pete - Season 3, Episode 4: Splashdown!",
      "episode": "S3E4",
      "season": 3,
      "episodeNumber": 4,
      "cycleInfo": "Post 757 - 7363 available (9.3% excluded from seasonal pool)"
    },
    {
      "imageName": "S02E05_-_Time_Tunnel-0011.jpg",
      "timestamp": "2025-11-14T15:06:56.541Z",
      "altText": "The Adventures of Pete & Pete - Season 2, Episode 5: Time Tunnel",
      "episode": "S2E5",
      "season": 2,
      "episodeNumber": 5,
      "cycleInfo": "Post 758 - 7362 available (9.3% excluded from seasonal pool)"
    },
    {
      "imageName": "S02E02_-_Field_of_Pete-0066.jpg",
      "timestamp": "2025-11-14T15:35:58.577Z",
      "altText": "The Adventures of Pete & Pete - Season 2, Episode 2: Field of Pete",
      "episode": "S2E2",
      "season": 2,
      "episodeNumber": 2,
      "cycleInfo": "Post 759 - 7361 available (9.3% excluded from seasonal pool)"
    },
    {
      "imageName": "S02E10_-_Farewell_My_Little_Viking_Part_1-0051.jpg",
      "timestamp": "2025-11-14T16:07:18.440Z",
      "altText": "The Adventures of Pete & Pete - Season 2, Episode 10: Farewell My Little Viking Part 1",
      "episode": "S2E10",
      "season": 2,
      "episodeNumber": 10,
      "cycleInfo": "Post 760 - 7360 available (9.4% excluded from seasonal pool)"
    },
    {
      "imageName": "S00E03_-_Space,_Geeks,_and_Johnny_Unitas-0144.jpg",
      "timestamp": "2025-11-14T16:41:21.933Z",
      "altText": "The Adventures of Pete & Pete - Space, Geeks, and Johnny Unitas",
      "episode": "S0E3",
      "season": 0,
      "episodeNumber": 3,
      "cycleInfo": "Post 761 - 7359 available (9.4% excluded from seasonal pool)"
    },
    {
      "imageName": "S01E01_-_King_of_The_Road-0217.jpg",
      "timestamp": "2025-11-14T17:05:48.685Z",
      "altText": "The Adventures of Pete & Pete - Season 1, Episode 1: King of the Road",
      "episode": "S1E1",
      "season": 1,
      "episodeNumber": 1,
      "cycleInfo": "Post 762 - 7358 available (9.4% excluded from seasonal pool)"
    },
    {
      "imageName": "S02E08_-_X_equals_Why-0113.jpg",
      "timestamp": "2025-11-14T17:36:55.273Z",
      "altText": "The Adventures of Pete & Pete - Season 2, Episode 8: X Equals Why",
      "episode": "S2E8",
      "season": 2,
      "episodeNumber": 8,
      "cycleInfo": "Post 763 - 7357 available (9.4% excluded from seasonal pool)"
    },
    {
      "imageName": "S02E05_-_Time_Tunnel-0093.jpg",
      "timestamp": "2025-11-14T18:08:43.867Z",
      "altText": "The Adventures of Pete & Pete - Season 2, Episode 5: Time Tunnel",
      "episode": "S2E5",
      "season": 2,
      "episodeNumber": 5,
      "cycleInfo": "Post 764 - 7356 available (9.4% excluded from seasonal pool)"
    },
    {
      "imageName": "The_Adventures_of_Pete_&_Pete_-_0x26_-_StareMaster-0033.jpg",
      "timestamp": "2025-11-14T18:42:21.831Z",
      "altText": "The Adventures of Pete & Pete - Staremaster",
      "episode": "S0E26",
      "season": 0,
      "episodeNumber": 26,
      "cycleInfo": "Post 765 - 7355 available (9.4% excluded from seasonal pool)"
    },
    {
      "imageName": "S03E09_-_Road_Warrior-0098.jpg",
      "timestamp": "2025-11-14T19:05:39.211Z",
      "altText": "The Adventures of Pete & Pete - Season 3, Episode 9: Road Warrior",
      "episode": "S3E9",
      "season": 3,
      "episodeNumber": 9,
      "cycleInfo": "Post 766 - 7354 available (9.4% excluded from seasonal pool)"
    },
    {
      "imageName": "The_Adventures_of_Pete_&_Pete_-_0x09_-_Flossing-0009.jpg",
      "timestamp": "2025-11-14T19:34:17.792Z",
      "altText": "The Adventures of Pete & Pete - Flossing",
      "episode": "S0E9",
      "season": 0,
      "episodeNumber": 9,
      "cycleInfo": "Post 767 - 7353 available (9.4% excluded from seasonal pool)"
    },
    {
      "imageName": "S02E05_-_Time_Tunnel-0273.jpg",
      "timestamp": "2025-11-14T20:07:27.863Z",
      "altText": "The Adventures of Pete & Pete - Season 2, Episode 5: Time Tunnel",
      "episode": "S2E5",
      "season": 2,
      "episodeNumber": 5,
      "cycleInfo": "Post 768 - 7352 available (9.5% excluded from seasonal pool)"
    },
    {
      "imageName": "S01E07_-_When_Petes_Collide-0098.jpg",
      "timestamp": "2025-11-14T20:37:09.123Z",
      "altText": "The Adventures of Pete & Pete - Season 1, Episode 7: When Petes Collide",
      "episode": "S1E7",
      "season": 1,
      "episodeNumber": 7,
      "cycleInfo": "Post 769 - 7351 available (9.5% excluded from seasonal pool)"
    },
    {
      "imageName": "S03E04_-_Splashdown!-0147.jpg",
      "timestamp": "2025-11-14T21:05:34.542Z",
      "altText": "The Adventures of Pete & Pete - Season 3, Episode 4: Splashdown!",
      "episode": "S3E4",
      "season": 3,
      "episodeNumber": 4,
      "cycleInfo": "Post 770 - 7350 available (9.5% excluded from seasonal pool)"
    },
    {
      "imageName": "S01E01_-_King_of_The_Road-0029.jpg",
      "timestamp": "2025-11-14T21:34:59.726Z",
      "altText": "The Adventures of Pete & Pete - Season 1, Episode 1: King of the Road",
      "episode": "S1E1",
      "season": 1,
      "episodeNumber": 1,
      "cycleInfo": "Post 771 - 7349 available (9.5% excluded from seasonal pool)"
    },
    {
      "imageName": "S03E07_-_Last_Laugh-0068.jpg",
      "timestamp": "2025-11-14T22:06:26.003Z",
      "altText": "The Adventures of Pete & Pete - Season 3, Episode 7: Last Laugh",
      "episode": "S3E7",
      "season": 3,
      "episodeNumber": 7,
      "cycleInfo": "Post 772 - 7348 available (9.5% excluded from seasonal pool)"
    },
    {
      "imageName": "S02E13_-_Sick_Day-0141.jpg",
      "timestamp": "2025-11-14T22:37:29.343Z",
      "altText": "The Adventures of Pete & Pete - Season 2, Episode 13: Sick Day",
      "episode": "S2E13",
      "season": 2,
      "episodeNumber": 13,
      "cycleInfo": "Post 773 - 7347 available (9.5% excluded from seasonal pool)"
    },
    {
      "imageName": "S01E05_-_Tool_and_Die-0096.jpg",
      "timestamp": "2025-11-14T23:07:16.198Z",
      "altText": "The Adventures of Pete & Pete - Season 1, Episode 5: Tool and Die",
      "episode": "S1E5",
      "season": 1,
      "episodeNumber": 5,
      "cycleInfo": "Post 774 - 7346 available (9.5% excluded from seasonal pool)"
    },
    {
      "imageName": "S02E11_-_Farewell_My_Little_Viking_Part_2-0173.jpg",
      "timestamp": "2025-11-14T23:35:15.145Z",
      "altText": "The Adventures of Pete & Pete - Season 2, Episode 11: Farewell My Little Viking Part 2",
      "episode": "S2E11",
      "season": 2,
      "episodeNumber": 11,
      "cycleInfo": "Post 775 - 7345 available (9.5% excluded from seasonal pool)"
    },
    {
      "imageName": "S02E01_-_Grounded_For_Life-0091.jpg",
      "timestamp": "2025-11-15T00:25:17.537Z",
      "altText": "The Adventures of Pete & Pete - Season 2, Episode 1: Grounded for Life",
      "episode": "S2E1",
      "season": 2,
      "episodeNumber": 1,
      "cycleInfo": "Post 776 - 7344 available (9.6% excluded from seasonal pool)"
    }
  ],
  "lastUpdated": "2025-11-15T00:25:17.537Z"
}